ukrainian_word_stress/__init__.py
ukrainian_word_stress/cli.py
ukrainian_word_stress/compile_dict.py
ukrainian_word_stress/mutable_text.py
ukrainian_word_stress/stressify_.py
ukrainian_word_stress/tags.py
ukrainian_word_stress/version.py
ukrainian_word_stress/data/stress.trie
ukrainian_word_stress-1.1.1.dist-info/LICENSE
ukrainian_word_stress-1.1.1.dist-info/METADATA
ukrainian_word_stress-1.1.1.dist-info/WHEEL
ukrainian_word_stress-1.1.1.dist-info/entry_points.txt
ukrainian_word_stress-1.1.1.dist-info/top_level.txt
ukrainian_word_stress-1.1.1.dist-info/RECORD
