Metadata-Version: 2.1
Name: ukrainian_word_stress
Version: 1.1.1
Summary: Find word stress for texts in Ukrainian
Home-page: https://github.com/lang-uk/ukrainian-word-stress
Author: Oleksiy Syvokon
Author-email: oleksiy.syvokon@gmail.com
License: MIT
Keywords: ukrainian nlp word stress accents dictionary linguistics
Classifier: Development Status :: 3 - Alpha
Classifier: Intended Audience :: Developers
Classifier: Programming Language :: Python :: 3
Classifier: Programming Language :: Python :: 3.7
Classifier: Programming Language :: Python :: 3.8
Classifier: Programming Language :: Python :: 3.9
Classifier: Programming Language :: Python :: 3.10
Classifier: Programming Language :: Python :: 3.11
Classifier: Programming Language :: Python :: 3.12
Classifier: License :: OSI Approved :: MIT License
License-File: LICENSE
Requires-Dist: stanza
Requires-Dist: marisa-trie
Provides-Extra: dev
Requires-Dist: tqdm ; extra == 'dev'
Requires-Dist: ua-gec ; extra == 'dev'
Provides-Extra: test
Requires-Dist: pytest ; extra == 'test'
Requires-Dist: coverage ; extra == 'test'
